setup.py
geek_tutorial_vid.egg-info/PKG-INFO
geek_tutorial_vid.egg-info/SOURCES.txt
geek_tutorial_vid.egg-info/dependency_links.txt
geek_tutorial_vid.egg-info/requires.txt
geek_tutorial_vid.egg-info/top_level.txt
modes/__init__.py