Metadata-Version: 2.1
Name: geek-tutorial-vid
Version: 1.0.2
Summary: simple tutorial package
Author: geek
